pcypher/__init__.py
pcypher/main.py
pcypher/parsetab.py
pcypher/pcypher.py
pcypher-0.1.0.dist-info/METADATA
pcypher-0.1.0.dist-info/WHEEL
pcypher-0.1.0.dist-info/entry_points.txt
pcypher-0.1.0.dist-info/licenses/LICENSE
pcypher-0.1.0.dist-info/RECORD
