Metadata-Version: 2.4
Name: pcypher
Version: 0.1.0
Summary: pcypher is a Python library to parse Cypher queries.
Project-URL: Homepage, https://github.com/rioriost/homebrew-pcypher
Project-URL: Issues, https://github.com/rioriost/homebrew-pcypher/issues
Author-email: Rio Fujita <rifujita@microsoft.com>
License: MIT License
License-File: LICENSE
Requires-Python: >=3.9.21
Requires-Dist: ply>=3.11
